MANIFEST.in
README.rst
setup.cfg
setup.py
airflow_kubernetes_job_operator/__init__.py
airflow_kubernetes_job_operator/collections.py
airflow_kubernetes_job_operator/config.py
airflow_kubernetes_job_operator/exceptions.py
airflow_kubernetes_job_operator/job_runner.py
airflow_kubernetes_job_operator/kubernetes_job_operator.py
airflow_kubernetes_job_operator/kubernetes_job_operator.py.default.yaml
airflow_kubernetes_job_operator/kubernetes_legacy_job_operator.py
airflow_kubernetes_job_operator/utils.py
airflow_kubernetes_job_operator/kube_api/__init__.py
airflow_kubernetes_job_operator/kube_api/client.py
airflow_kubernetes_job_operator/kube_api/collections.py
airflow_kubernetes_job_operator/kube_api/config.py
airflow_kubernetes_job_operator/kube_api/exceptions.py
airflow_kubernetes_job_operator/kube_api/operations.py
airflow_kubernetes_job_operator/kube_api/queries.py
airflow_kubernetes_job_operator/kube_api/utils.py
airflow_kubernetes_job_operator/kube_api/watchers.py
airflow_kubernetes_job_operator/templates/job_default.yaml
airflow_kubernetes_job_operator/templates/pod_default.yaml
airflow_kubernetes_job_operator_eks_auth.egg-info/PKG-INFO
airflow_kubernetes_job_operator_eks_auth.egg-info/SOURCES.txt
airflow_kubernetes_job_operator_eks_auth.egg-info/dependency_links.txt
airflow_kubernetes_job_operator_eks_auth.egg-info/requires.txt
airflow_kubernetes_job_operator_eks_auth.egg-info/top_level.txt