Metadata-Version: 1.2
Name: airflow-kubernetes-job-operator-eks-auth
Version: 1.0.3
Summary: An airflow job operator that executes a task as a Kubernetes job on a cluster, given a job yaml configuration or an image uri.
Home-page: https://github.com/duferdev/KubernetesJobOperator
Author: Victor Dubé
Author-email: 
License: LICENSE
Platform: any
Requires-Python: >=3.6
